xx_fft_lab/xx_fft_lab.srcs/sources_1/new/dds_core.vhd
----------------------------------------------------------------------------------
-- Company: 
-- Engineer: 
-- 
-- Create Date: 03/27/2026 07:29:54 PM
-- Design Name: 
-- Module Name: dds_core - Behavioral
-- Project Name: 
-- Target Devices: 
-- Tool Versions: 
-- Description: 
-- 
-- Dependencies: 
-- 
-- Revision:
-- Revision 0.01 - File Created
-- Additional Comments:
-- 
----------------------------------------------------------------------------------


library ieee;
use ieee.std_logic_1164.all;

-- Uncomment the following library declaration if using
-- arithmetic functions with Signed or Unsigned values
use ieee.numeric_std.ALL;

-- Uncomment the following library declaration if instantiating
-- any Xilinx leaf cells in this code.
--library unisim;
--use unisim.vcomponents.all;

entity dds_core is
  port
  (
    --使用差分输入的时钟对产生的单端时钟信号, 1.2v LVDS
    clk       : in std_logic;
    --复位信号，低电平有效
    rst_n       : in std_logic;
    --使能信号，高电平有效
    en          : in std_logic;
    --频率控制字，32位，无符号步进值
    freq_word   : in std_logic_vector(31 downto 0);
    --输出正弦采样值，16位，最高位为符号位，表示当前正弦波的幅值
    sample_out  : out std_logic_vector(15 downto 0);
    --输出数据有效信号，当sample_out上的数据有效时，该信号为高电平
    valid       : out std_logic
  );
end dds_core;

architecture behavioral of dds_core is 
--相位累加器，32位无符号，每个时钟周期根据频率控制字增加相应的值
signal phase_accumulator: unsigned(31 downto 0) := (others => '0');
--查表地址
--前两位为象限标志，00表示第一象限，01表示第二象限，10表示第三象限，11表示第四象限
--后八位为象限内地址，访问1024/4深度的四分之一正弦波查找表
signal current_table_addr: unsigned(9 downto 0) := (others => '0');
--四分之一正弦波查找表地址，9位，表示当前相位在四分之一周期内的地址
signal quarter_addr: unsigned(8 downto 0) := (others => '0');
--是否需要对查表值取反的标志，第一和第二象限不需要取反，第三和第四象限需要取反
signal if_negate: std_logic := '0';
signal if_negate_reg: std_logic := '0';
--当前查表得到的正弦波采样值，16位有符号，表示当前相位对应的正弦波幅值
signal current_table_value: signed(15 downto 0) := (others => '0');
--四分之一正弦波查找表，1024/4个采样点，每个采样点16位有符号，表示对应相位的正弦波幅值
type sin_table_type is array(0 to 256) of signed(15 downto 0);
--预先计算好的四分之一周期正弦波查找表，使用16位有符号整数表示幅值，范围从0到32767
constant sin_table: sin_table_type := 
(
  0 => to_signed(0, 16),
  1 => to_signed(201, 16),
  2 => to_signed(402, 16),
  3 => to_signed(603, 16),
  4 => to_signed(804, 16),
  5 => to_signed(1005, 16),
  6 => to_signed(1206, 16),
  7 => to_signed(1407, 16),
  8 => to_signed(1608, 16),
  9 => to_signed(1809, 16),
  10 => to_signed(2009, 16),
  11 => to_signed(2210, 16),
  12 => to_signed(2410, 16),
  13 => to_signed(2611, 16),
  14 => to_signed(2811, 16),
  15 => to_signed(3012, 16),
  16 => to_signed(3212, 16),
  17 => to_signed(3412, 16),
  18 => to_signed(3612, 16),
  19 => to_signed(3811, 16),
  20 => to_signed(4011, 16),
  21 => to_signed(4210, 16),
  22 => to_signed(4410, 16),
  23 => to_signed(4609, 16),
  24 => to_signed(4808, 16),
  25 => to_signed(5007, 16),
  26 => to_signed(5205, 16),
  27 => to_signed(5404, 16),
  28 => to_signed(5602, 16),
  29 => to_signed(5800, 16),
  30 => to_signed(5998, 16),
  31 => to_signed(6195, 16),
  32 => to_signed(6393, 16),
  33 => to_signed(6590, 16),
  34 => to_signed(6786, 16),
  35 => to_signed(6983, 16),
  36 => to_signed(7179, 16),
  37 => to_signed(7375, 16),
  38 => to_signed(7571, 16),
  39 => to_signed(7767, 16),
  40 => to_signed(7962, 16),
  41 => to_signed(8157, 16),
  42 => to_signed(8351, 16),
  43 => to_signed(8545, 16),
  44 => to_signed(8739, 16),
  45 => to_signed(8933, 16),
  46 => to_signed(9126, 16),
  47 => to_signed(9319, 16),
  48 => to_signed(9512, 16),
  49 => to_signed(9704, 16),
  50 => to_signed(9896, 16),
  51 => to_signed(10087, 16),
  52 => to_signed(10278, 16),
  53 => to_signed(10469, 16),
  54 => to_signed(10659, 16),
  55 => to_signed(10849, 16),
  56 => to_signed(11039, 16),
  57 => to_signed(11228, 16),
  58 => to_signed(11417, 16),
  59 => to_signed(11605, 16),
  60 => to_signed(11793, 16),
  61 => to_signed(11980, 16),
  62 => to_signed(12167, 16),
  63 => to_signed(12353, 16),
  64 => to_signed(12539, 16),
  65 => to_signed(12725, 16),
  66 => to_signed(12910, 16),
  67 => to_signed(13094, 16),
  68 => to_signed(13279, 16),
  69 => to_signed(13462, 16),
  70 => to_signed(13645, 16),
  71 => to_signed(13828, 16),
  72 => to_signed(14010, 16),
  73 => to_signed(14191, 16),
  74 => to_signed(14372, 16),
  75 => to_signed(14553, 16),
  76 => to_signed(14732, 16),
  77 => to_signed(14912, 16),
  78 => to_signed(15090, 16),
  79 => to_signed(15269, 16),
  80 => to_signed(15446, 16),
  81 => to_signed(15623, 16),
  82 => to_signed(15800, 16),
  83 => to_signed(15976, 16),
  84 => to_signed(16151, 16),
  85 => to_signed(16325, 16),
  86 => to_signed(16499, 16),
  87 => to_signed(16673, 16),
  88 => to_signed(16846, 16),
  89 => to_signed(17018, 16),
  90 => to_signed(17189, 16),
  91 => to_signed(17360, 16),
  92 => to_signed(17530, 16),
  93 => to_signed(17700, 16),
  94 => to_signed(17869, 16),
  95 => to_signed(18037, 16),
  96 => to_signed(18204, 16),
  97 => to_signed(18371, 16),
  98 => to_signed(18537, 16),
  99 => to_signed(18703, 16),
  100 => to_signed(18868, 16),
  101 => to_signed(19032, 16),
  102 => to_signed(19195, 16),
  103 => to_signed(19357, 16),
  104 => to_signed(19519, 16),
  105 => to_signed(19680, 16),
  106 => to_signed(19841, 16),
  107 => to_signed(20000, 16),
  108 => to_signed(20159, 16),
  109 => to_signed(20317, 16),
  110 => to_signed(20475, 16),
  111 => to_signed(20631, 16),
  112 => to_signed(20787, 16),
  113 => to_signed(20942, 16),
  114 => to_signed(21096, 16),
  115 => to_signed(21250, 16),
  116 => to_signed(21403, 16),
  117 => to_signed(21554, 16),
  118 => to_signed(21705, 16),
  119 => to_signed(21856, 16),
  120 => to_signed(22005, 16),
  121 => to_signed(22154, 16),
  122 => to_signed(22301, 16),
  123 => to_signed(22448, 16),
  124 => to_signed(22594, 16),
  125 => to_signed(22739, 16),
  126 => to_signed(22884, 16),
  127 => to_signed(23027, 16),
  128 => to_signed(23170, 16),
  129 => to_signed(23311, 16),
  130 => to_signed(23452, 16),
  131 => to_signed(23592, 16),
  132 => to_signed(23731, 16),
  133 => to_signed(23870, 16),
  134 => to_signed(24007, 16),
  135 => to_signed(24143, 16),
  136 => to_signed(24279, 16),
  137 => to_signed(24413, 16),
  138 => to_signed(24547, 16),
  139 => to_signed(24680, 16),
  140 => to_signed(24811, 16),
  141 => to_signed(24942, 16),
  142 => to_signed(25072, 16),
  143 => to_signed(25201, 16),
  144 => to_signed(25329, 16),
  145 => to_signed(25456, 16),
  146 => to_signed(25582, 16),
  147 => to_signed(25708, 16),
  148 => to_signed(25832, 16),
  149 => to_signed(25955, 16),
  150 => to_signed(26077, 16),
  151 => to_signed(26198, 16),
  152 => to_signed(26319, 16),
  153 => to_signed(26438, 16),
  154 => to_signed(26556, 16),
  155 => to_signed(26674, 16),
  156 => to_signed(26790, 16),
  157 => to_signed(26905, 16),
  158 => to_signed(27019, 16),
  159 => to_signed(27133, 16),
  160 => to_signed(27245, 16),
  161 => to_signed(27356, 16),
  162 => to_signed(27466, 16),
  163 => to_signed(27575, 16),
  164 => to_signed(27683, 16),
  165 => to_signed(27790, 16),
  166 => to_signed(27896, 16),
  167 => to_signed(28001, 16),
  168 => to_signed(28105, 16),
  169 => to_signed(28208, 16),
  170 => to_signed(28310, 16),
  171 => to_signed(28411, 16),
  172 => to_signed(28510, 16),
  173 => to_signed(28609, 16),
  174 => to_signed(28706, 16),
  175 => to_signed(28803, 16),
  176 => to_signed(28898, 16),
  177 => to_signed(28992, 16),
  178 => to_signed(29085, 16),
  179 => to_signed(29177, 16),
  180 => to_signed(29268, 16),
  181 => to_signed(29358, 16),
  182 => to_signed(29447, 16),
  183 => to_signed(29534, 16),
  184 => to_signed(29621, 16),
  185 => to_signed(29706, 16),
  186 => to_signed(29791, 16),
  187 => to_signed(29874, 16),
  188 => to_signed(29956, 16),
  189 => to_signed(30037, 16),
  190 => to_signed(30117, 16),
  191 => to_signed(30195, 16),
  192 => to_signed(30273, 16),
  193 => to_signed(30349, 16),
  194 => to_signed(30424, 16),
  195 => to_signed(30498, 16),
  196 => to_signed(30571, 16),
  197 => to_signed(30643, 16),
  198 => to_signed(30714, 16),
  199 => to_signed(30783, 16),
  200 => to_signed(30852, 16),
  201 => to_signed(30919, 16),
  202 => to_signed(30985, 16),
  203 => to_signed(31050, 16),
  204 => to_signed(31113, 16),
  205 => to_signed(31176, 16),
  206 => to_signed(31237, 16),
  207 => to_signed(31297, 16),
  208 => to_signed(31356, 16),
  209 => to_signed(31414, 16),
  210 => to_signed(31470, 16),
  211 => to_signed(31526, 16),
  212 => to_signed(31580, 16),
  213 => to_signed(31633, 16),
  214 => to_signed(31685, 16),
  215 => to_signed(31736, 16),
  216 => to_signed(31785, 16),
  217 => to_signed(31833, 16),
  218 => to_signed(31880, 16),
  219 => to_signed(31926, 16),
  220 => to_signed(31971, 16),
  221 => to_signed(32014, 16),
  222 => to_signed(32057, 16),
  223 => to_signed(32098, 16),
  224 => to_signed(32137, 16),
  225 => to_signed(32176, 16),
  226 => to_signed(32213, 16),
  227 => to_signed(32250, 16),
  228 => to_signed(32285, 16),
  229 => to_signed(32318, 16),
  230 => to_signed(32351, 16),
  231 => to_signed(32382, 16),
  232 => to_signed(32412, 16),
  233 => to_signed(32441, 16),
  234 => to_signed(32469, 16),
  235 => to_signed(32495, 16),
  236 => to_signed(32521, 16),
  237 => to_signed(32545, 16),
  238 => to_signed(32567, 16),
  239 => to_signed(32589, 16),
  240 => to_signed(32609, 16),
  241 => to_signed(32628, 16),
  242 => to_signed(32646, 16),
  243 => to_signed(32663, 16),
  244 => to_signed(32678, 16),
  245 => to_signed(32692, 16),
  246 => to_signed(32705, 16),
  247 => to_signed(32717, 16),
  248 => to_signed(32728, 16),
  249 => to_signed(32737, 16),
  250 => to_signed(32745, 16),
  251 => to_signed(32752, 16),
  252 => to_signed(32757, 16),
  253 => to_signed(32761, 16),
  254 => to_signed(32765, 16),
  255 => to_signed(32766, 16),
  256 => to_signed(32767, 16)
);
--用于寄存valid信号的寄存器，保证在时钟上升沿时能够正确地将当前的象限标志和查表值传递到输出阶段
signal valid_reg_1: std_logic := '0';
begin
  --根据相位累加器的高10位计算当前的查表地址
  current_table_addr <= phase_accumulator(31 downto 22);
  --根据查表地址的高两位确定当前的象限，根据查表地址的低八位确定当前在四分之一周期内的地址，并根据象限标志确定是否需要对查表值取反
  process(current_table_addr) begin
    case current_table_addr(9 downto 8) is
      when "00" =>
        quarter_addr <= current_table_addr(8 downto 0);
        if_negate <= '0';
      when "01" =>
        quarter_addr <= to_unsigned(511, 9) - current_table_addr(8 downto 0) + to_unsigned(1, 9);
        if_negate <= '0';
      when "10" =>
        quarter_addr <= current_table_addr(8 downto 0);
        if_negate <= '1';
      when "11" =>
        quarter_addr <= to_unsigned(511, 9) - current_table_addr(8 downto 0) + to_unsigned(1, 9);
        if_negate <= '1';
      when others =>
        quarter_addr <= (others => '0');
        if_negate <= '0';
    end case;
  end process;

  --根据四分之一周期内的地址从查找表中获取当前的正弦波采样值
  process(clk) begin
    if rising_edge(clk) then
      if rst_n = '0' then
        if_negate_reg <= '0';
        current_table_value <= (others => '0');
        valid_reg_1 <= '0';
      elsif en = '1' then
        if_negate_reg <= if_negate;
        current_table_value <= sin_table(to_integer(quarter_addr));
        valid_reg_1 <= '1';
      else
        valid_reg_1 <= '0';
      end if;
    end if;
  end process;

  process(clk) begin
    if rising_edge(clk) then
      if rst_n = '0' then
        --复位时，清零相位累加器和输出采样值，并将valid信号置低
        sample_out <= (others => '0');
        phase_accumulator <= (others => '0');
        valid <= '0';
      else
        if en = '1' then
          phase_accumulator <= phase_accumulator + unsigned(freq_word);
        end if;
        if valid_reg_1 = '1' then
          if if_negate_reg = '1' then
            sample_out <= std_logic_vector(-current_table_value);
          else
            sample_out <= std_logic_vector(current_table_value);
          end if;
          valid <= '1';
          
        else
          valid <= '0';
        end if;
      end if;
    end if;
  end process;
end behavioral;

xx_fft_lab/xx_fft_lab.srcs/sim_1/new/tb_dds_core.sv
`timescale 1ns / 1ps
//////////////////////////////////////////////////////////////////////////////////
// Company: 
// Engineer: 
// 
// Create Date: 03/27/2026 07:30:26 PM
// Design Name: 
// Module Name: tb_dds_core
// Project Name: 
// Target Devices: 
// Tool Versions: 
// Description: 
// 
// Dependencies: 
// 
// Revision:
// Revision 0.01 - File Created
// Additional Comments:
// 
//////////////////////////////////////////////////////////////////////////////////

`timescale 1ns/1ps
module tb_dds_core();

//时间间隔和模拟周期数
parameter real CLK_PERIOD = 5.0;
parameter int SIMULATE_CYCLES = 10000;

logic             clk       ;
logic             rst_n     ;
logic             en        ;
logic     [31:0]  freq_word ;
logic     [15:0]  sample_out;
logic             valid     ;

//统计变量
integer  file_handle;
integer  sample_count;
real phase_inc;

//时钟生成
initial begin
  clk = 0;
end

always #(CLK_PERIOD/2) begin
  clk = ~clk;
end

//实例化DDS核心模块
dds_core u_dds_core
(
  .clk        (clk),
  .rst_n      (rst_n),
  .en         (en),
  .freq_word  (freq_word),
  .sample_out (sample_out),
  .valid      (valid)
);

//测试序列
initial begin
  rst_n         = 0;
  en            = 0;
  freq_word     = 0;
  sample_count  = 0;

  //初始化统计变量
  $display("DDS TB start, clk frequency: %0.2f MHz. ", 1000.0/CLK_PERIOD);
  #100;
  rst_n = 1;
  $display("[%0t ns] Reset deasserted. ", $time);
  #100;

  //测试1：设置频率字为0.005 * 2^32，目标频率为1 MHz
  freq_word = 32'h147AE14; // 0.005 * 2^32 = 21474836.48
  phase_inc = real'(freq_word) / (2.0 ** 32) * 200.0; // 200 MHz * 0.005 = 1 MHz
  $display("[%0t ns] test 1: setting freq_word to %0d (target 1mhz, actual %0.3f mhz). ", $time, freq_word, phase_inc);
  en = 1;
  $display("[%0t ns] DDS enabled. ", $time);
  #(CLK_PERIOD * 1000);
  $display("[%0t ns] test 1 finished 1000 cycles. ", $time);
  
  en = 0;
  $display("[%0t ns] DDS disabled. ", $time);
  #(CLK_PERIOD * 100);

  //测试2：设置频率字为0.05 * 2^32，目标频率为10 MHz
  freq_word = 32'hCCCCCCD; //0.05 * 2^32 = 214748364.8
  phase_inc = real'(freq_word) / (2.0 ** 32) * 200.0; // 200 MHz * 0.05 = 10 MHz
  $display("[%0t ns] test 2: setting freq_word to %0d (target 10mhz, actual %0.3f mhz). ", $time, freq_word, phase_inc);
  en = 1;
  $display("[%0t ns] DDS enabled. ", $time);
  #(CLK_PERIOD * 1000);
  $display("[%0t ns] test 2 finished 1000 cycles. ", $time);

  en = 0;
  $display("[%0t ns] DDS disabled. ", $time);
  #(CLK_PERIOD * 100);
  $display("tb completed, total simulate time: %0t ns. ", $time);

  $finish;
end

//统计输出
always @(posedge clk) begin
  if(valid) begin
    sample_count = sample_count + 1;

    if (sample_count % 5 == 0) begin
      $display("[%0t ns] sample #%0d: %0d(0x%0h). ", $time, sample_count, $signed(sample_out), sample_out);
    end
  end
end

//波形生成
initial begin
  $dumpfile("tb_dds_core.vcd");
  $dumpvars(0, tb_dds_core);
end

//断言检查
always @(posedge clk) begin
  if (!rst_n && $time > 10) begin
    assert (sample_out == 0) 
      else   $error("[%0t ns] Error: sample_out is not zero during reset. ", $time);
    assert (valid == 0) 
      else   $error("[%0t ns] Error: valid is not zero during reset. ", $time);
  end
end

//当DDS被禁用时，valid应该保持为0
property p_valid_when_disabled;
  @(posedge clk) disable iff(!rst_n) (!en) |-> ##[0:3] (valid == 0);
endproperty

assert property (p_valid_when_disabled) 
else $error("[%0t ns] Error: valid is not zero when DDS is disabled. ", $time);

//统计最大值和最小值
real max_value;
real min_value;
real current_value;

initial begin
  max_value = -32768.0;
  min_value = 32767.0;
end

always @(posedge clk) begin
  if (valid) begin
    current_value = $signed(sample_out);
    if (current_value > max_value) begin
      max_value = current_value;
    end
    if (current_value < min_value) begin
      min_value = current_value;
    end
  end
end

final begin
  $display("statistics: total samples: %0d, max value: %0.2f, min value: %0.2f, peak-to-peak: %0.2f. ", sample_count, max_value, min_value, max_value - min_value);
end

endmodule

xx_fft_lab/xx_fft_lab.sim/sim_1/behav/xsim/tb_dds_core.vcd
$date
   Wed Apr  1 00:24:32 2026
$end
$version
  2023.1
$end
$timescale
  1ps
$end
$scope module tb_dds_core $end
$var reg 1 ! clk $end
$var reg 1 " rst_n $end
$var reg 1 # en $end
$var reg 32 $ freq_word [31:0] $end
$var reg 16 % sample_out [15:0] $end
$var reg 1 & valid $end
$var integer 32 ' file_handle [31:0] $end
$var integer 32 ( sample_count [31:0] $end
$var real 32 ) phase_inc $end
$var real 32 * max_value $end
$var real 32 + min_value $end
$var real 32 , current_value $end
$scope module u_dds_core $end
$var wire 1 - clk $end
$var wire 1 . rst_n $end
$var wire 1 / en $end
$var wire 32 0 freq_word $end
$var wire 16 1 sample_out $end
$var wire 1 2 valid $end
$var wire 32 3 phase_accumulator $end
$var wire 10 4 current_table_addr $end
$var wire 9 5 quarter_addr $end
$var wire 1 6 if_negate $end
$var wire 1 7 if_negate_reg $end
$var wire 16 8 current_table_value $end
$var wire 1 9 valid_reg_1 $end
$upscope $end
$upscope $end
$enddefinitions $end
#0
$dumpvars
0!
0"
0#
b0 $
bx %
x&
bx '
b0 (
r0 )
r-32768 *
r32767 +
r0 ,
0-
0.
0/
b0 0
bx 1
x2
b0 3
b0 4
b0 5
06
07
b0 8
09
$end
#2500
1!
b0 %
0&
1-
b0 1
#5000
0!
0-
#7500
1!
1-
#10000
0!
0-
#12500
1!
1-
#15000
0!
0-
#17500
1!
1-
#20000
0!
0-
#22500
1!
1-
#25000
0!
0-
#27500
1!
1-
#30000
0!
0-
#32500
1!
1-
#35000
0!
0-
#37500
1!
1-
#40000
0!
0-
#42500
1!
1-
#45000
0!
0-
#47500
1!
1-
#50000
0!
0-
#52500
1!
1-
#55000
0!
0-
#57500
1!
1-
#60000
0!
0-
#62500
1!
1-
#65000
0!
0-
#67500
1!
1-
#70000
0!
0-
#72500
1!
1-
#75000
0!
0-
#77500
1!
1-
#80000
0!
0-
#82500
1!
1-
#85000
0!
0-
#87500
1!
1-
#90000
0!
0-
#92500
1!
1-
#95000
0!
0-
#97500
1!
1-
#100000
0!
1"
0-
1.
#102500
1!
1-
#105000
0!
0-
#107500
1!
1-
#110000
0!
0-
#112500
1!
1-
#115000
0!
0-
#117500
1!
1-
#120000
0!
0-
#122500
1!
1-
#125000
0!
0-
#127500
1!
1-
#130000
0!
0-
#132500
1!
1-
#135000
0!
0-
#137500
1!
1-
#140000
0!
0-
#142500
1!
1-
#145000
0!
0-
#147500
1!
1-
#150000
0!
0-
#152500
1!
1-
#155000
0!
0-
#157500
1!
1-
#160000
0!
0-
#162500
1!
1-
#165000
0!
0-
#167500
1!
1-
#170000
0!
0-
#172500
1!
1-
#175000
0!
0-
#177500
1!
1-
#180000
0!
0-
#182500
1!
1-
#185000
0!
0-
#187500
1!
1-
#190000
0!
0-
#192500
1!
1-
#195000
0!
0-
#197500
1!
1-
#200000
0!
1#
b1010001111010111000010100 $
r0.9999999776482582 )
0-
1/
b1010001111010111000010100 0
#202500
1!
1-
b1010001111010111000010100 3
19
#205000
0!
0-
#207500
1!
1&
1-
12
b10100011110101110000101000 3
b1010 5
#210000
0!
0-
#212500
1!
b1111101101 %
b1 (
r0 *
r0 +
1-
b11110101110000101000111100 3
b11111011001 8
#215000
0!
0-
#217500
1!
b11111011001 %
b10 (
r1005 *
r1005 ,
1-
b11111011001 1
b101000111101011100001010000 3
b10100 4
b10100 5
b101111000100 8
#220000
0!
0-
#222500
1!
b101111000100 %
b11 (
r2009 *
r2009 ,
1-
b101111000100 1
b110011001100110011001100100 3
b11001 5
b111110101011 8
#225000
0!
0-
#227500
1!
b111110101011 %
b100 (
r3012 *
r3012 ,
1-
b111110101011 1
b111101011100001010001111000 3
b1001110001111 8
#230000
0!
0-
#232500
1!
b1001110001111 %
b101 (
r4011 *
r4011 ,
1-
b1001110001111 1
b1000111101011100001010001100 3
b100011 4
b100011 5
b1011101101110 8
#235000
0!
0-
#237500
1!
b1011101101110 %
b110 (
r5007 *
r5007 ,
1-
b1011101101110 1
b1010001111010111000010100000 3
b101000 5
b1101101000111 8
#240000
0!
0-
#242500
1!
b1101101000111 %
b111 (
r5998 *
r5998 ,
1-
b1101101000111 1
b1011100001010001111010110100 3
b1111100011010 8
#245000
0!
0-
#247500
1!
b1111100011010 %
b1000 (
r6983 *
r6983 ,
1-
b1111100011010 1
b1100110011001100110011001000 3
b110011 4
b110011 5
b10001110100110 8
#250000
0!
0-
#252500
1!
b10001110100110 %
b1001 (
r7962 *
r7962 ,
1-
b10001110100110 1
b1110000101000111101011011100 3
b111000 5
b10011101100111 8
#255000
0!
0-
#257500
1!
b10011101100111 %
b1010 (
r9126 *
r9126 ,
1-
b10011101100111 1
b1111010111000010100011110000 3
b10101100011111 8
#260000
0!
0-
#262500
1!
b10101100011111 %
b1011 (
r10087 *
r10087 ,
1-
b10101100011111 1
b10000101000111101011100000100 3
b1000010 4
b1000010 5
b10111011001100 8
#265000
0!
0-
#267500
1!
b10111011001100 %
b1100 (
r11039 *
r11039 ,
1-
b10111011001100 1
b10001111010111000010100011000 3
b11001001101110 8
#270000
0!
0-
#272500
1!
b11001001101110 %
b1101 (
r11980 *
r11980 ,
1-
b11001001101110 1
b10011001100110011001100101100 3
b1001100 5
b11011000000100 8
#275000
0!
0-
#277500
1!
b11011000000100 %
b1110 (
r12910 *
r12910 ,
1-
b11011000000100 1
b10100011110101110000101000000 3
b1010001 4
b1010001 5
b11100110001100 8
#280000
0!
0-
#282500
1!
b11100110001100 %
b1111 (
r13828 *
r13828 ,
1-
b11100110001100 1
b10101110000101000111101010100 3
b11110100000111 8
#285000
0!
0-
#287500
1!
b11110100000111 %
b10000 (
r14732 *
r14732 ,
1-
b11110100000111 1
b10111000010100011110101101000 3
b1011100 5
b100000100100001 8
#290000
0!
0-
#292500
1!
b100000100100001 %
b10001 (
r15623 *
r15623 ,
1-
b100000100100001 1
b11000010100011110101101111100 3
b1100001 4
b1100001 5
b100010001111010 8
#295000
0!
0-
#297500
1!
b100010001111010 %
b10010 (
r16673 *
r16673 ,
1-
b100010001111010 1
b11001100110011001100110010000 3
#300000
0!
0-
#302500
1!
b100011111000011 %
b10011 (
r17530 *
r17530 ,
1-
b11010111000010100011110100100 3
b1101011 5
b100101011111011 8
#305000
0!
0-
#307500
1!
b100101011111011 %
b10100 (
r18371 *
r18371 ,
1-
b100101011111011 1
b11100001010001111010110111000 3
b1110000 4
b1110000 5
b100111000100000 8
#310000
0!
0-
#312500
1!
b100111000100000 %
b10101 (
r19195 *
r19195 ,
1-
b100111000100000 1
b11101011100001010001111001100 3
b101000100110011 8
#315000
0!
0-
#317500
1!
b101000100110011 %
b10110 (
r20000 *
r20000 ,
1-
b101000100110011 1
b11110101110000101000111100000 3
b1111010 5
b101010000110010 8
#320000
0!
0-
#322500
1!
b101010000110010 %
b10111 (
r20787 *
r20787 ,
1-
b101010000110010 1
b11111111111111111111111110100 3
#325000
0!
0-
#327500
1!
b101011100011101 %
b11000 (
r21554 *
r21554 ,
1-
b100001010001111010111000001000 3
b10000101 4
b10000101 5
b101100111110011 8
#330000
0!
0-
#332500
1!
b101100111110011 %
b11001 (
r22301 *
r22301 ,
1-
b101100111110011 1
b100010100011110101110000011100 3
b10001010 5
b101110100111110 8
#335000
0!
0-
#337500
1!
b101110100111110 %
b11010 (
r23027 *
r23027 ,
1-
b101110100111110 1
b100011110101110000101000110000 3
#340000
0!
0-
#342500
1!
b101111111100011 %
b11011 (
r23870 *
r23870 ,
1-
b100101000111101011100001000100 3
b10010100 4
b10010100 5
b110001001110001 8
#345000
0!
0-
#347500
1!
b110001001110001 %
b11100 (
r24547 *
r24547 ,
1-
b110001001110001 1
b100110011001100110011001011000 3
b10011001 5
b110010011101000 8
#350000
0!
0-
#352500
1!
b110010011101000 %
b11101 (
r25201 *
r25201 ,
1-
b110010011101000 1
b100111101011100001010001101100 3
#355000
0!
0-
#357500
1!
b110011101000110 %
b11110 (
r25832 *
r25832 ,
1-
b101000111101011100001010000000 3
b10100011 4
b10100011 5
b110100110001011 8
#360000
0!
0-
#362500
1!
b110100110001011 %
b11111 (
r26438 *
r26438 ,
1-
b110100110001011 1
b101010001111010111000010010100 3
b10101000 5
#365000
0!
0-
#367500
1!
b110101110110111 %
b100000 (
r27019 *
r27019 ,
1-
b101011100001010001111010101000 3
b110110111001001 8
#370000
0!
0-
#372500
1!
b110110111001001 %
b100001 (
r27575 *
r27575 ,
1-
b110110111001001 1
b101100110011001100110010111100 3
b10110011 4
b10110011 5
b111000000100010 8
#375000
0!
0-
#377500
1!
b111000000100010 %
b100010 (
r28105 *
r28105 ,
1-
b111000000100010 1
b101110000101000111101011010000 3
b10111000 5
#380000
0!
0-
#382500
1!
b111000111111001 %
b100011 (
r28706 *
r28706 ,
1-
b101111010111000010100011100100 3
#385000
0!
0-
#387500
1!
b111001110110101 %
b100100 (
r29177 *
r29177 ,
1-
b110000101000111101011011111000 3
b11000010 4
b11000010 5
b111010101010101 8
#390000
0!
0-
#392500
1!
b111010101010101 %
b100101 (
r29621 *
r29621 ,
1-
b111010101010101 1
b110001111010111000010100001100 3
#395000
0!
0-
#397500
1!
b111011011011000 %
b100110 (
r30037 *
r30037 ,
1-
b110011001100110011001100100000 3
b11001100 5
b111100000111111 8
#400000
0!
0-
#402500
1!
b111100000111111 %
b100111 (
r30424 *
r30424 ,
1-
b111100000111111 1
b110100011110101110000100110100 3
b11010001 4
b11010001 5
#405000
0!
0-
#407500
1!
b111100110001001 %
b101000 (
r30783 *
r30783 ,
1-
b110101110000101000111101001000 3
#410000
0!
0-
#412500
1!
b111101010110110 %
b101001 (
r31113 *
r31113 ,
1-
b110111000010100011110101011100 3
b11011100 5
#415000
0!
0-
#417500
1!
b111101111111000 %
b101010 (
r31414 *
r31414 ,
1-
b111000010100011110101101110000 3
b11100001 4
b11100001 5
b111110011100011 8
#420000
0!
0-
#422500
1!
b111110011100011 %
b101011 (
r31736 *
r31736 ,
1-
b111110011100011 1
b111001100110011001100110000100 3
#425000
0!
0-
#427500
1!
b111110110110000 %
b101100 (
r31971 *
r31971 ,
1-
b111010111000010100011110011000 3
b11101011 5
#430000
0!
0-
#432500
1!
b111111001011111 %
b101101 (
r32176 *
r32176 ,
1-
b111100001010001111010110101100 3
b11110000 4
b11110000 5
#435000
0!
0-
#437500
1!
b111111011101111 %
b101110 (
r32351 *
r32351 ,
1-
b111101011100001010001111000000 3
#440000
0!
0-
#442500
1!
b111111101100001 %
b101111 (
r32495 *
r32495 ,
1-
b111110101110000101000111010100 3
b11111010 5
#445000
0!
0-
#447500
1!
b111111110110100 %
b110000 (
r32609 *
r32609 ,
1-
b111111111111111111111111101000 3
#450000
0!
0-
#452500
1!
b111111111101001 %
b110001 (
r32692 *
r32692 ,
1-
b1000001010001111010110111111100 3
b100000101 4
#455000
0!
0-
#457500
1!
b111111111111110 %
b110010 (
r32745 *
r32745 ,
1-
b1000010100011110101110000010000 3
b11110110 5
#460000
0!
0-
#462500
1!
b111111111110000 %
b110011 (
r32766 *
r32766 ,
1-
b1000011110101110000101000100100 3
#465000
0!
0-
#467500
1!
b111111111000001 %
b110100 (
r32752 ,
1-
b1000101000111101011100000111000 3
b100010100 4
b11101100 5
#470000
0!
0-
#472500
1!
b111111101110100 %
b110101 (
r32705 ,
1-
b1000110011001100110011001001100 3
b11100111 5
#475000
0!
0-
#477500
1!
b111111100001001 %
b110110 (
r32628 ,
1-
b1000111101011100001010001100000 3
#480000
0!
0-
#482500
1!
b111111001111110 %
b110111 (
r32521 ,
1-
b1001000111101011100001001110100 3
b100100011 4
b11011101 5
#485000
0!
0-
#487500
1!
b111110111010101 %
b111000 (
r32382 ,
1-
b1001010001111010111000010001000 3
#490000
0!
0-
#492500
1!
b111110100001110 %
b111001 (
r32213 ,
1-
b1001011100001010001111010011100 3
b11010010 5
#495000
0!
0-
#497500
1!
b111110000101001 %
b111010 (
r32014 ,
1-
b1001100110011001100110010110000 3
b100110011 4
b11001101 5
b111101011101110 8
#500000
0!
0-
#502500
1!
b111101011101110 %
b111011 (
r31785 ,
1-
b111101011101110 1
b1001110000101000111101011000100 3
#505000
0!
0-
#507500
1!
b111100111001000 %
b111100 (
r31470 ,
1-
b1001111010111000010100011011000 3
b11000011 5
#510000
0!
0-
#512500
1!
b111100010000100 %
b111101 (
r31176 ,
1-
b1010000101000111101011011101100 3
b101000010 4
b10111110 5
b111011100100010 8
#515000
0!
0-
#517500
1!
b111011100100010 %
b111110 (
r30852 ,
1-
b111011100100010 1
b1010001111010111000010100000000 3
#520000
0!
0-
#522500
1!
b111010110100101 %
b111111 (
r30498 ,
1-
b1010011001100110011001100010100 3
b10110100 5
#525000
0!
0-
#527500
1!
b111010000001010 %
b1000000 (
r30117 ,
1-
b1010100011110101110000100101000 3
b101010001 4
b10101111 5
b111001001010100 8
#530000
0!
0-
#532500
1!
b111001001010100 %
b1000001 (
r29706 ,
1-
b111001001010100 1
b1010101110000101000111100111100 3
#535000
0!
0-
#537500
1!
b111000010000011 %
b1000010 (
r29268 ,
1-
b1010111000010100011110101010000 3
b10100100 5
b110111000110000 8
#540000
0!
0-
